pasi/__init__.py
pasi/acc_functions.py
pasi/loss_functions.py
pasi/pasi_methods.py
pasi-0.2.0.dist-info/licenses/LICENSE
pasi-0.2.0.dist-info/METADATA
pasi-0.2.0.dist-info/WHEEL
pasi-0.2.0.dist-info/top_level.txt
pasi-0.2.0.dist-info/RECORD
