Metadata-Version: 2.4
Name: pasi
Version: 0.2.0
Summary: Prediction Accuracy Subgroup Identification - Find subgroups with differential model performance
Home-page: https://github.com/yourusername/pasi
Author: Ruotao Zhang
Author-email: zrtpublic@gmail.com
Classifier: Programming Language :: Python :: 3
Classifier: License :: OSI Approved :: MIT License
Classifier: Operating System :: OS Independent
Classifier: Intended Audience :: Science/Research
Classifier: Topic :: Scientific/Engineering :: Artificial Intelligence
Requires-Python: >=3.6
License-File: LICENSE
Requires-Dist: numpy
Requires-Dist: scipy
Requires-Dist: scikit-learn
Requires-Dist: joblib
Requires-Dist: numba
Requires-Dist: pandas
Requires-Dist: progressbar2
Dynamic: author
Dynamic: author-email
Dynamic: classifier
Dynamic: description
Dynamic: description-content-type
Dynamic: home-page
Dynamic: license-file
Dynamic: requires-dist
Dynamic: requires-python
Dynamic: summary
